MANIFEST.in
README.rst
setup.cfg
setup.py
distconfig/__init__.py
distconfig/api.py
distconfig/config.py
distconfig/utils.py
distconfig.egg-info/PKG-INFO
distconfig.egg-info/SOURCES.txt
distconfig.egg-info/dependency_links.txt
distconfig.egg-info/requires.txt
distconfig.egg-info/top_level.txt
distconfig/backends/__init__.py
distconfig/backends/base.py
distconfig/backends/consul.py
distconfig/backends/etcd.py
distconfig/backends/execution_context.py
distconfig/backends/zookeeper.py
distconfig/tests/__init__.py
distconfig/tests/integration/__init__.py
distconfig/tests/integration/base.py
distconfig/tests/integration/test_consul_backend.py
distconfig/tests/integration/test_etcd_backend.py
distconfig/tests/integration/test_zookeeper_backend.py
distconfig/tests/unit/__init__.py
distconfig/tests/unit/test_backend.py
distconfig/tests/unit/test_config.py
requirements/base.txt
requirements/dev.txt