Metadata-Version: 1.0
Name: distconfig
Version: 0.1.0
Summary: Library to manage configuration using Zookeeper, Etcd, Consul
Home-page: http://github.com/deliveryhero/distconfig/
Author: Mouad Benchchaoui
Author-email: mouad.benchchaoui@deliveryhero.com
License: Apache License, Version 2.0
Keywords: Configuration management zookeeper etcd consul
Platform: UNKNOWN
Classifier: Programming Language :: Python
Classifier: License :: OSI Approved :: Apache Software License
Classifier: Operating System :: OS Independent
Classifier: Programming Language :: Python :: 2
Classifier: Programming Language :: Python :: 2.7
Classifier: Programming Language :: Python :: 3
Classifier: Programming Language :: Python :: 3.3
Classifier: Programming Language :: Python :: 3.4
Classifier: Topic :: Internet
Classifier: Topic :: Software Development :: Libraries :: Python Modules
Classifier: Intended Audience :: Developers
